pytgasu/__init__.py
pytgasu/cli.py
pytgasu/constants.py
pytgasu/defgen/__init__.py
pytgasu/defgen/defgen.py
pytgasu/prepare/__init__.py
pytgasu/prepare/defgen.py
pytgasu/prepare/manipulation.py
pytgasu/upload/__init__.py
pytgasu/upload/defparse.py
pytgasu/upload/uploader.py
pytgasu/uploader/__init__.py
pytgasu/uploader/customised_session.py
pytgasu/uploader/defparse.py
pytgasu/uploader/uploader.py
pytgasu-0.2.1.dist-info/METADATA
pytgasu-0.2.1.dist-info/RECORD
pytgasu-0.2.1.dist-info/WHEEL
pytgasu-0.2.1.dist-info/entry_points.txt
pytgasu-0.2.1.dist-info/top_level.txt
pytgasu-0.2.1.dist-info/zip-safe
