Metadata-Version: 2.1
Name: pytgasu
Version: 0.2.1
Summary: Telegram sticker sets creation automated (partially).
Home-page: https://github.com/alemonmk/pytgasu
Author: Lemon Lam
Author-email: almk@rmntn.net
License: GPLv3
Keywords: Telegram,stickers
Platform: UNKNOWN
Classifier: Development Status :: 3 - Alpha
Classifier: Intended Audience :: End Users/Desktop
Classifier: Topic :: Communications :: Chat
Classifier: License :: OSI Approved :: GNU General Public License v3 (GPLv3)
Classifier: Programming Language :: Python :: 3 :: Only
Classifier: Programming Language :: Python :: 3.6
Requires-Python: >=3.5
Provides-Extra: test
Requires-Dist: setuptools (>=30.3.0)
Requires-Dist: Telethon (==0.18.1.1)
Requires-Dist: click
Requires-Dist: Pillow
Provides-Extra: test
Requires-Dist: nose; extra == 'test'
Requires-Dist: coverage; extra == 'test'
